decompy/__init__.py
decompy/interfaces/__init__.py
decompy/interfaces/lsnresult.py
decompy/interfaces/pcaresult.py
decompy/interfaces/rankfactorresult.py
decompy/interfaces/svdresult.py
decompy/matrix_factorization/__init__.py
decompy/matrix_factorization/adm.py
decompy/matrix_factorization/alm.py
decompy/matrix_factorization/asrpca.py
decompy/matrix_factorization/dual.py
decompy/matrix_factorization/ealm.py
decompy/matrix_factorization/fpcp.py
decompy/matrix_factorization/ga.py
decompy/matrix_factorization/ialm.py
decompy/matrix_factorization/l1f.py
decompy/matrix_factorization/ladmap.py
decompy/matrix_factorization/mog.py
decompy/matrix_factorization/op.py
decompy/matrix_factorization/pcp.py
decompy/matrix_factorization/regl1alm.py
decompy/matrix_factorization/rsvddpd.py
decompy/matrix_factorization/sadal.py
decompy/matrix_factorization/svt.py
decompy/matrix_factorization/vbrpca.py
decompy/rankmethods/__init__.py
decompy/rankmethods/bayes.py
decompy/rankmethods/cvrank.py
decompy/rankmethods/penalized.py
decompy/utils/__init__.py
decompy/utils/bayesmethods.py
decompy/utils/constants.py
decompy/utils/matrixmethods.py
decompy/utils/rootmethods.py
decompy/utils/simmethods.py
decompy/utils/validations.py
decompy-1.1.1.dist-info/LICENSE
decompy-1.1.1.dist-info/METADATA
decompy-1.1.1.dist-info/WHEEL
decompy-1.1.1.dist-info/top_level.txt
decompy-1.1.1.dist-info/RECORD
