Metadata-Version: 2.1
Name: decompy
Version: 1.1.1
Summary: A python package containing several robust algorithms for matrix decomposition, rank estimation and relevant analysis.
Author-email: Subhrajyoty Roy <subhrajyotyroy@gmail.com>
License: BSD 3-Clause License
Project-URL: Homepage, https://github.com/subroy13/decompy
Project-URL: Repository, https://github.com/subroy13/decompy.git
Project-URL: Bug Tracker, https://github.com/subroy13/decompy/issues
Project-URL: Changelog, https://github.com/subroy13/decompy/blob/master/CHANGELOG.md
Classifier: Programming Language :: Python :: 3
Classifier: Operating System :: OS Independent
Requires-Python: >=3.9
License-File: LICENSE
Requires-Dist: numpy >=1.23
Requires-Dist: tqdm
Requires-Dist: scipy
